pyel/__init__.py
pyel/expression_language.py
PyEL-0.0.2.dist-info/LICENSE
PyEL-0.0.2.dist-info/METADATA
PyEL-0.0.2.dist-info/WHEEL
PyEL-0.0.2.dist-info/top_level.txt
PyEL-0.0.2.dist-info/RECORD
