Metadata-Version: 2.1
Name: PyEL
Version: 0.0.2
Summary: This project aims to facilitate the execution of codes before and after a method using decorator.
Home-page: https://github.com/diogodilcl/PyEL
Author: Diogo Dil
Author-email: diogodicl@gmail.com
License: Apache License 2.0
Platform: UNKNOWN
Classifier: Programming Language :: Python
Classifier: Programming Language :: Python :: 3
Classifier: Programming Language :: Python :: 3.6
Classifier: Programming Language :: Python :: 3.7
Classifier: Programming Language :: Python :: 3 :: Only
Classifier: Operating System :: OS Independent
Classifier: Topic :: Software Development :: Libraries
